agentix_notifications/__init__.py
agentix_notifications/config.py
agentix_notifications/email/__init__.py
agentix_notifications/email/notifications.py
agentix_notifications/whatsapp/__init__.py
agentix_notifications/whatsapp/base.py
agentix_notifications/whatsapp/notifications.py
agentix_notifications/whatsapp/novomind.py
agentix_notifications-0.0.3.dist-info/licenses/LICENSE
agentix_notifications-0.0.3.dist-info/METADATA
agentix_notifications-0.0.3.dist-info/WHEEL
agentix_notifications-0.0.3.dist-info/top_level.txt
agentix_notifications-0.0.3.dist-info/RECORD
