Metadata-Version: 2.4
Name: agentix-notifications
Version: 0.0.3
Summary: Notifications plugin for Agentix platform (WhatsApp, Email)
License-Expression: Apache-2.0
Project-URL: Homepage, https://github.com/FIDOX/py-plugin-agentix-notifications
Project-URL: Bug Tracker, https://github.com/FIDOX/py-plugin-agentix-notifications/issues
Requires-Python: >=3.8
License-File: LICENSE
Requires-Dist: aiohttp>=3.8.0
Requires-Dist: requests
Provides-Extra: dev
Requires-Dist: agentix-core; extra == "dev"
Dynamic: license-file
